[
  {
    "type": "constructor",
    "inputs": [
      {
        "name": "paymentAuthority_",
        "type": "address",
        "internalType": "address"
      },
      {
        "name": "redemptionAuthority_",
        "type": "address",
        "internalType": "address"
      }
    ],
    "stateMutability": "nonpayable"
  },
  {
    "type": "function",
    "name": "DOMAIN_SEPARATOR",
    "inputs": [],
    "outputs": [
      {
        "name": "",
        "type": "bytes32",
        "internalType": "bytes32"
      }
    ],
    "stateMutability": "view"
  },
  {
    "type": "function",
    "name": "MAX_KNOWN_SCHEMA_VERSION",
    "inputs": [],
    "outputs": [
      {
        "name": "",
        "type": "uint16",
        "internalType": "uint16"
      }
    ],
    "stateMutability": "view"
  },
  {
    "type": "function",
    "name": "PAYMENT_AUTHORITY",
    "inputs": [],
    "outputs": [
      {
        "name": "",
        "type": "address",
        "internalType": "address"
      }
    ],
    "stateMutability": "view"
  },
  {
    "type": "function",
    "name": "REDEMPTION_AUTHORITY",
    "inputs": [],
    "outputs": [
      {
        "name": "",
        "type": "address",
        "internalType": "address"
      }
    ],
    "stateMutability": "view"
  },
  {
    "type": "function",
    "name": "balance",
    "inputs": [
      {
        "name": "userId",
        "type": "bytes32",
        "internalType": "bytes32"
      }
    ],
    "outputs": [
      {
        "name": "",
        "type": "uint256",
        "internalType": "uint256"
      }
    ],
    "stateMutability": "view"
  },
  {
    "type": "function",
    "name": "credit",
    "inputs": [
      {
        "name": "userId",
        "type": "bytes32",
        "internalType": "bytes32"
      },
      {
        "name": "amount",
        "type": "uint256",
        "internalType": "uint256"
      },
      {
        "name": "attestationNonce",
        "type": "uint64",
        "internalType": "uint64"
      },
      {
        "name": "schemaVersion",
        "type": "uint16",
        "internalType": "uint16"
      },
      {
        "name": "expiresAt",
        "type": "uint64",
        "internalType": "uint64"
      },
      {
        "name": "signature",
        "type": "bytes",
        "internalType": "bytes"
      }
    ],
    "outputs": [
      {
        "name": "newBalance",
        "type": "uint256",
        "internalType": "uint256"
      }
    ],
    "stateMutability": "nonpayable"
  },
  {
    "type": "function",
    "name": "hashCredit",
    "inputs": [
      {
        "name": "userId",
        "type": "bytes32",
        "internalType": "bytes32"
      },
      {
        "name": "amount",
        "type": "uint256",
        "internalType": "uint256"
      },
      {
        "name": "attestationNonce",
        "type": "uint64",
        "internalType": "uint64"
      },
      {
        "name": "schemaVersion",
        "type": "uint16",
        "internalType": "uint16"
      },
      {
        "name": "expiresAt",
        "type": "uint64",
        "internalType": "uint64"
      }
    ],
    "outputs": [
      {
        "name": "",
        "type": "bytes32",
        "internalType": "bytes32"
      }
    ],
    "stateMutability": "view"
  },
  {
    "type": "function",
    "name": "hashRedemption",
    "inputs": [
      {
        "name": "userId",
        "type": "bytes32",
        "internalType": "bytes32"
      },
      {
        "name": "amount",
        "type": "uint256",
        "internalType": "uint256"
      },
      {
        "name": "attestationNonce",
        "type": "uint64",
        "internalType": "uint64"
      },
      {
        "name": "schemaVersion",
        "type": "uint16",
        "internalType": "uint16"
      },
      {
        "name": "expiresAt",
        "type": "uint64",
        "internalType": "uint64"
      }
    ],
    "outputs": [
      {
        "name": "",
        "type": "bytes32",
        "internalType": "bytes32"
      }
    ],
    "stateMutability": "view"
  },
  {
    "type": "function",
    "name": "nonce",
    "inputs": [
      {
        "name": "userId",
        "type": "bytes32",
        "internalType": "bytes32"
      }
    ],
    "outputs": [
      {
        "name": "",
        "type": "uint64",
        "internalType": "uint64"
      }
    ],
    "stateMutability": "view"
  },
  {
    "type": "function",
    "name": "redeem",
    "inputs": [
      {
        "name": "userId",
        "type": "bytes32",
        "internalType": "bytes32"
      },
      {
        "name": "amount",
        "type": "uint256",
        "internalType": "uint256"
      },
      {
        "name": "attestationNonce",
        "type": "uint64",
        "internalType": "uint64"
      },
      {
        "name": "schemaVersion",
        "type": "uint16",
        "internalType": "uint16"
      },
      {
        "name": "expiresAt",
        "type": "uint64",
        "internalType": "uint64"
      },
      {
        "name": "signature",
        "type": "bytes",
        "internalType": "bytes"
      }
    ],
    "outputs": [
      {
        "name": "newBalance",
        "type": "uint256",
        "internalType": "uint256"
      }
    ],
    "stateMutability": "nonpayable"
  },
  {
    "type": "event",
    "name": "Credited",
    "inputs": [
      {
        "name": "userId",
        "type": "bytes32",
        "indexed": true,
        "internalType": "bytes32"
      },
      {
        "name": "amount",
        "type": "uint256",
        "indexed": false,
        "internalType": "uint256"
      },
      {
        "name": "newBalance",
        "type": "uint256",
        "indexed": false,
        "internalType": "uint256"
      },
      {
        "name": "nonce",
        "type": "uint64",
        "indexed": false,
        "internalType": "uint64"
      },
      {
        "name": "schemaVersion",
        "type": "uint16",
        "indexed": false,
        "internalType": "uint16"
      }
    ],
    "anonymous": false
  },
  {
    "type": "event",
    "name": "Redeemed",
    "inputs": [
      {
        "name": "userId",
        "type": "bytes32",
        "indexed": true,
        "internalType": "bytes32"
      },
      {
        "name": "amount",
        "type": "uint256",
        "indexed": false,
        "internalType": "uint256"
      },
      {
        "name": "newBalance",
        "type": "uint256",
        "indexed": false,
        "internalType": "uint256"
      },
      {
        "name": "nonce",
        "type": "uint64",
        "indexed": false,
        "internalType": "uint64"
      },
      {
        "name": "schemaVersion",
        "type": "uint16",
        "indexed": false,
        "internalType": "uint16"
      }
    ],
    "anonymous": false
  },
  {
    "type": "error",
    "name": "ErrAttestationExpired",
    "inputs": []
  },
  {
    "type": "error",
    "name": "ErrInsufficientBalance",
    "inputs": []
  },
  {
    "type": "error",
    "name": "ErrInvalidSignature",
    "inputs": []
  },
  {
    "type": "error",
    "name": "ErrNonceTooLow",
    "inputs": []
  },
  {
    "type": "error",
    "name": "ErrUnauthorizedSigner",
    "inputs": []
  },
  {
    "type": "error",
    "name": "ErrUnsupportedSchemaVersion",
    "inputs": []
  },
  {
    "type": "error",
    "name": "ErrZeroAuthority",
    "inputs": []
  }
]
